dendritic_arborization_tracer/__init__.py
dendritic_arborization_tracer/__main__.py
dendritic_arborization_tracer/img.py
dendritic_arborization_tracer/logger.py
dendritic_arborization_tracer/minimal_DAT.py
dendritic_arborization_tracer/minimal_DAT_GUI.py
dendritic_arborization_tracer/paint.py
dendritic_arborization_tracer/vectorial.py
dendritic_arborization_tracer-0.1.dist-info/METADATA
dendritic_arborization_tracer-0.1.dist-info/WHEEL
dendritic_arborization_tracer-0.1.dist-info/top_level.txt
dendritic_arborization_tracer-0.1.dist-info/RECORD
