Metadata-Version: 2.1
Name: dendritic-arborization-tracer
Version: 0.1
Summary: A tool to segment dendrites
Home-page: https://github.com/baigouy/DAT
Author: Benoit Aigouy
Author-email: baigouy@gmail.com
License: BSD
Platform: UNKNOWN
Classifier: Programming Language :: Python :: 3
Classifier: License :: OSI Approved :: BSD License
Classifier: Operating System :: OS Independent
Requires-Python: >=3.6
Requires-Dist: opencv-python
Requires-Dist: czifile
Requires-Dist: matplotlib
Requires-Dist: numpy
Requires-Dist: numpydoc
Requires-Dist: Pillow
Requires-Dist: PyQt5
Requires-Dist: PyQtWebEngine
Requires-Dist: read-lif
Requires-Dist: scikit-image
Requires-Dist: scipy
Requires-Dist: tifffile
Requires-Dist: natsort
Requires-Dist: numexpr
